Metadata-Version: 2.1
Name: typed-decorator
Version: 1.0.0
Summary: Module for type decorator
Home-page: https://github.com/Miha77777py/typed
Author: Miha77777
Author-email: lv11miha@gmail.com
